traffic_light.v
module traffic_light(
    input clk,
    input reset,
    output reg [1:0] light
);
    // Encode states
    localparam RED    = 2'b00;
    localparam GREEN  = 2'b01;
    localparam YELLOW = 2'b10;

    reg [1:0] state;
    reg [3:0] counter;

    always @(posedge clk or posedge reset) begin
        if (reset) begin
            state <= RED;
            counter <= 0;
        end else begin
            counter <= counter + 1;

            case (state)
                RED: begin
                    if (counter == 4) begin
                        state <= GREEN;
                        counter <= 0;
                    end
                end

                GREEN: begin
                    if (counter == 3) begin
                        state <= YELLOW;
                        counter <= 0;
                    end
                end

                YELLOW: begin
                    if (counter == 2) begin
                        state <= RED;
                        counter <= 0;
                    end
                end
            endcase
        end
    end

    // Output light = state
    always @(*) begin
        light = state;
    end
endmodule

tb_traffic.v
`timescale 1ns/1ps

module tb_traffic;
    reg clk;
    reg reset;
    wire [1:0] light;

    // Instantiate DUT
    traffic_light TL (
        .clk(clk),
        .reset(reset),
        .light(light)
    );

    // Clock - 10ns period
    initial begin
        clk = 0;
        forever #5 clk = ~clk;
    end

    // Simulation + Waveform dump
    initial begin
        $display("Simulation started...");

        // VCD dump
        $dumpfile("traffic.vcd");
        $dumpvars(0, tb_traffic);  // Dump EVERYTHING in tb_traffic
        $dumpvars(0, TL);          // Dump DUT internals explicitly

        reset = 1;
        #20 reset = 0;

        #200;  // Run long enough to generate wave activity
        $display("Simulation ending...");
        $finish;
    end
endmodule

traffic.vcd
$date
	Fri Dec 12 13:35:01 2025
$end
$version
	Icarus Verilog
$end
$timescale
	1ps
$end
$scope module tb_traffic $end
$var wire 2 ! light [1:0] $end
$var reg 1 " clk $end
$var reg 1 # reset $end
$scope module TL $end
$var wire 1 " clk $end
$var wire 1 # reset $end
$var parameter 2 $ GREEN $end
$var parameter 2 % RED $end
$var parameter 2 & YELLOW $end
$var reg 4 ' counter [3:0] $end
$var reg 2 ( light [1:0] $end
$var reg 2 ) state [1:0] $end
$upscope $end
$upscope $end
$scope module tb_traffic $end
$scope module TL $end
$upscope $end
$upscope $end
$enddefinitions $end
$comment Show the parameter values. $end
$dumpall
b10 &
b0 %
b1 $
$end
#0
$dumpvars
b0 )
b0 (
b0 '
1#
0"
b0 !
$end
#5000
1"
#10000
0"
#15000
1"
#20000
0"
0#
#25000
b1 '
1"
#30000
0"
#35000
b10 '
1"
#40000
0"
#45000
b11 '
1"
#50000
0"
#55000
b100 '
1"
#60000
0"
#65000
b1 !
b1 (
b1 )
b0 '
1"
#70000
0"
#75000
b1 '
1"
#80000
0"
#85000
b10 '
1"
#90000
0"
#95000
b11 '
1"
#100000
0"
#105000
b10 !
b10 (
b10 )
b0 '
1"
#110000
0"
#115000
b1 '
1"
#120000
0"
#125000
b10 '
1"
#130000
0"
#135000
b0 !
b0 (
b0 )
b0 '
1"
#140000
0"
#145000
b1 '
1"
#150000
0"
#155000
b10 '
1"
#160000
0"
#165000
b11 '
1"
#170000
0"
#175000
b100 '
1"
#180000
0"
#185000
b1 !
b1 (
b1 )
b0 '
1"
#190000
0"
#195000
b1 '
1"
#200000
0"
#205000
b10 '
1"
#210000
0"
#215000
b11 '
1"
