trafficv2.v

`timescale 1ns/1ps 
`define Red 2'b00
`define Green 2'b11
`define Yellow 2'b01 
`define s0  3'b000//highway on gg country off
`define s1  3'b001//highway on 
`define s2  3'b010
`define s3  3'b011
`define s4  3'b100
`define s5  3'b101

////////////////////////Delays
`define YellowtoRed  7
`define RedtoGreen   7
`define s0tos1   9
`define s1tos2   7
`define s3tos4   9
/////////////////////////true and false

`define TRUE 1'b1
`define FALSE 1'b0

// small stub for char_detector so file compiles
module char_detector(
    input  wire [7:0] char,
    output wire       is_true1
);
    assign is_true1 = (char == 8'h41) ? 1'b1 : 1'b0; // 'A' example
endmodule


module first(hwy, country, X, B, clock, clear, hours, minutes, char, is_true, is_true1);

    // Port declarations (kept in your original order)
    output reg [1:0] hwy, country; // green yellow red
    input X; // for the traffic in day 
    input B; // for the a b c in night
    input clock, clear;
    input [4:0] hours;   
    input [5:0] minutes; 
    input [7:0] char;  

    // fixed: specify type for is_true and terminate is_true1 declaration with semicolon
    output reg is_true;  
    output wire is_true1;

    // internal regs
    reg [2:0] state;
    reg [2:0] next_state;

    initial begin
        state = `s0;
        next_state = `s0;
        hwy = `Green;
        country = `Red;
        is_true = `FALSE;
    end

    // synchronous state update
    always @(posedge clock) begin
        state <= next_state;
    end

    // outputs based on state
    always @(state) begin
        case (state)
            `s0: begin hwy=`Green;  country=`Red;   end
            `s1: begin hwy=`Green;  country=`Red;   end
            `s2: begin hwy=`Yellow; country=`Red;   end
            `s3: begin hwy=`Red;    country=`Green; end
            `s4: begin hwy=`Red;    country=`Yellow;end
            default: begin hwy=`Green; country=`Red; end
        endcase
    end

    // instantiate char_detector (single instance)
    char_detector char_det_inst (
        .char(char),
        .is_true1(is_true1)
    );

    // NOTE: original code used repeat(@posedge clock) inside combinational always.
    // That is illegal. To keep your logic structure and make the file syntactically
    // valid I left immediate transitions where timing was requested. Replace with
    // counters/timers on posedge clock when you want real delays.
    always @(state or clear or X or is_true1 or hours or minutes) begin
        if ((hours >= 5 && hours < 9) || (hours == 9 && minutes == 0)) begin
            if (clear) next_state = `s0;
            else begin
                case (state)
                    `s0: if (X) next_state = `s1; else if (is_true1) next_state = `s2; else next_state = `s0;
                    `s1: next_state = `s2;
                    `s2: next_state = `s3;
                    `s3: next_state = `s4;
                    `s4: next_state = `s0;
                    default: next_state = `s0;
                endcase
            end
        end else begin
            if (clear) next_state = `s0;
            else begin
                case (state)
                    `s0: if (is_true1) next_state = `s2; else next_state = `s0;
                    `s2: next_state = `s4;
                    `s4: next_state = `s0;
                    default: next_state = `s0;
                endcase
            end
        end
    end

endmodule

tb_trafficv2.v
// tb_trafficv2_fixed.v
`timescale 1ns/1ps

module tb_trafficv2;
    reg clk;
    reg clear;
    reg X;
    reg B;
    reg [4:0] hours;
    reg [5:0] minutes;
    reg [7:0] char;
    wire [1:0] hwy, country;
    wire is_true1;
    wire is_true;

    // Instantiate DUT
    first DUT (
        .hwy(hwy),
        .country(country),
        .X(X),
        .B(B),
        .clock(clk),
        .clear(clear),
        .hours(hours),
        .minutes(minutes),
        .char(char),
        .is_true(is_true),
        .is_true1(is_true1)
    );

    // clock
    initial begin
        clk = 0;
        forever #5 clk = ~clk; // 10 ns period
    end

    initial begin
        $display("Starting TB...");
        $dumpfile("trafficv2.vcd");
        $dumpvars(0, tb_trafficv2);

        // initial stimulus
        clear = 1; X = 0; B = 0; hours = 4; minutes = 59; char = 8'h00;
        #12; clear = 0;

        // test: day time and an 'A' char to trigger detector
        #20; hours = 5; minutes = 0; char = 8'h41; // daytime begins
        #200;

        $display("Ending TB...");
        $finish;
    end
endmodule

trafficv2.vcd
$date
	Fri Dec 12 20:08:38 2025
$end
$version
	Icarus Verilog
$end
$timescale
	1ps
$end
$scope module tb_trafficv2 $end
$var wire 1 ! is_true1 $end
$var wire 1 " is_true $end
$var wire 2 # hwy [1:0] $end
$var wire 2 $ country [1:0] $end
$var reg 1 % B $end
$var reg 1 & X $end
$var reg 8 ' char [7:0] $end
$var reg 1 ( clear $end
$var reg 1 ) clk $end
$var reg 5 * hours [4:0] $end
$var reg 6 + minutes [5:0] $end
$scope module DUT $end
$var wire 1 % B $end
$var wire 1 & X $end
$var wire 8 , char [7:0] $end
$var wire 1 ( clear $end
$var wire 1 ) clock $end
$var wire 5 - hours [4:0] $end
$var wire 6 . minutes [5:0] $end
$var wire 1 ! is_true1 $end
$var reg 2 / country [1:0] $end
$var reg 2 0 hwy [1:0] $end
$var reg 1 " is_true $end
$var reg 3 1 next_state [2:0] $end
$var reg 3 2 state [2:0] $end
$scope module char_det_inst $end
$var wire 8 3 char [7:0] $end
$var wire 1 ! is_true1 $end
$upscope $end
$upscope $end
$upscope $end
$enddefinitions $end
$comment Show the parameter values. $end
$dumpall
$end
#0
$dumpvars
b0 3
b0 2
b0 1
b11 0
b0 /
b111011 .
b100 -
b0 ,
b111011 +
b100 *
0)
1(
b0 '
0&
0%
b0 $
b11 #
0"
0!
$end
#5000
1)
#10000
0)
#12000
0(
#15000
1)
#20000
0)
#25000
1)
#30000
0)
#32000
b10 1
1!
b1000001 '
b1000001 ,
b1000001 3
b0 +
b0 .
b101 *
b101 -
#35000
b11 1
b1 #
b1 0
b10 2
1)
#40000
0)
#45000
b100 1
b11 $
b11 /
b0 #
b0 0
b11 2
1)
#50000
0)
#55000
b0 1
b1 $
b1 /
b100 2
1)
#60000
0)
#65000
b10 1
b0 $
b0 /
b11 #
b11 0
b0 2
1)
#70000
0)
#75000
b11 1
b1 #
b1 0
b10 2
1)
#80000
0)
#85000
b100 1
b11 $
b11 /
b0 #
b0 0
b11 2
1)
#90000
0)
#95000
b0 1
b1 $
b1 /
b100 2
1)
#100000
0)
#105000
b10 1
b0 $
b0 /
b11 #
b11 0
b0 2
1)
#110000
0)
#115000
b11 1
b1 #
b1 0
b10 2
1)
#120000
0)
#125000
b100 1
b11 $
b11 /
b0 #
b0 0
b11 2
1)
#130000
0)
#135000
b0 1
b1 $
b1 /
b100 2
1)
#140000
0)
#145000
b10 1
b0 $
b0 /
b11 #
b11 0
b0 2
1)
#150000
0)
#155000
b11 1
b1 #
b1 0
b10 2
1)
#160000
0)
#165000
b100 1
b11 $
b11 /
b0 #
b0 0
b11 2
1)
#170000
0)
#175000
b0 1
b1 $
b1 /
b100 2
1)
#180000
0)
#185000
b10 1
b0 $
b0 /
b11 #
b11 0
b0 2
1)
#190000
0)
#195000
b11 1
b1 #
b1 0
b10 2
1)
#200000
0)
#205000
b100 1
b11 $
b11 /
b0 #
b0 0
b11 2
1)
#210000
0)
#215000
b0 1
b1 $
b1 /
b100 2
1)
#220000
0)
#225000
b10 1
b0 $
b0 /
b11 #
b11 0
b0 2
1)
