trafficv4.v
module smart_traffic_controller (
    input wire clk,
    input wire reset,

    // Control inputs
    input wire car_sensor,
    input wire pedestrian_req,
    input wire emergency,

    // Parking system
    input wire car_enter,
    input wire car_exit,

    // Outputs
    output reg [1:0] traffic_light,     // 00=RED, 01=YELLOW, 10=GREEN
    output reg pedestrian_green,
    output reg emergency_active,
    output reg [3:0] parking_slots
);

    // State encoding
    localparam s0_IDLE        = 3'b000;
    localparam s1_GREEN       = 3'b001;
    localparam s2_YELLOW      = 3'b010;
    localparam s3_RED         = 3'b011;
    localparam s4_EMERGENCY   = 3'b100;
    localparam s5_PEDESTRIAN  = 3'b101;

    reg [2:0] state, next_state;
    reg [3:0] timer;

    // -------------------- State Register --------------------
    always @(posedge clk or posedge reset) begin
        if (reset) begin
            state <= s0_IDLE;
            timer <= 0;
            parking_slots <= 4'd10;
        end else begin
            state <= next_state;

            // Reset timer whenever state changes
            if (state != next_state)
                timer <= 0;
            else
                timer <= timer + 1;
        end
    end

    // -------------------- Parking Slot Management --------------------
    always @(posedge clk) begin
        if (!reset) begin
            if (car_enter && parking_slots > 0)
                parking_slots <= parking_slots - 1;
            else if (car_exit && parking_slots < 10)
                parking_slots <= parking_slots + 1;
        end
    end

    // -------------------- Next State Logic --------------------
    always @(*) begin
        next_state = state;

        case (state)

            s0_IDLE:
                if (emergency)         next_state = s4_EMERGENCY;
                else if (pedestrian_req) next_state = s5_PEDESTRIAN;
                else if (car_sensor)     next_state = s1_GREEN;

            s1_GREEN:
                if (emergency)         next_state = s4_EMERGENCY;
                else if (timer == 4)   next_state = s2_YELLOW;

            s2_YELLOW:
                if (timer == 2)        next_state = s3_RED;

            s3_RED:
                if (timer == 3)        next_state = s0_IDLE;

            s5_PEDESTRIAN:
                if (timer == 3)        next_state = s0_IDLE;

            s4_EMERGENCY:
                if (!emergency)        next_state = s0_IDLE;

            default: next_state = s0_IDLE;
        endcase
    end

    // -------------------- Output Logic --------------------
    always @(*) begin
        traffic_light = 2'b00;
        pedestrian_green = 0;
        emergency_active = 0;

        case (state)
            s1_GREEN:    traffic_light = 2'b10;
            s2_YELLOW:   traffic_light = 2'b01;
            s3_RED:      traffic_light = 2'b00;

            s5_PEDESTRIAN: begin
                traffic_light = 2'b00;
                pedestrian_green = 1;
            end

            s4_EMERGENCY: begin
                traffic_light = 2'b10; // force GREEN
                emergency_active = 1;
            end
        endcase
    end

endmodule

tb_trafficv3.v
`timescale 1ns/1ps

module tb_smart_traffic_controller;

    reg clk;
    reg reset;
    reg car_sensor;
    reg pedestrian_req;
    reg emergency;
    reg car_enter;
    reg car_exit;

    wire [1:0] traffic_light;
    wire pedestrian_green;
    wire emergency_active;
    wire [3:0] parking_slots;

    // DUT
    smart_traffic_controller dut (
        .clk(clk),
        .reset(reset),
        .car_sensor(car_sensor),
        .pedestrian_req(pedestrian_req),
        .emergency(emergency),
        .car_enter(car_enter),
        .car_exit(car_exit),
        .traffic_light(traffic_light),
        .pedestrian_green(pedestrian_green),
        .emergency_active(emergency_active),
        .parking_slots(parking_slots)
    );

    // Clock: 10 ns period
    initial begin
        clk = 0;
        forever #5 clk = ~clk;
    end

    initial begin
        $dumpfile("smart_traffic.vcd");
        $dumpvars(0, tb_smart_traffic_controller);

        reset = 1;
        car_sensor = 0;
        pedestrian_req = 0;
        emergency = 0;
        car_enter = 0;
        car_exit = 0;

        #20 reset = 0;

        // Normal car request
        #20 car_sensor = 1;
        #10 car_sensor = 0;

        // Pedestrian request
        #60 pedestrian_req = 1;
        #10 pedestrian_req = 0;

        // Emergency override
        #80 emergency = 1;
        #40 emergency = 0;

        // Parking activity
        #20 car_enter = 1;
        #10 car_enter = 0;

        #20 car_exit = 1;
        #10 car_exit = 0;

        #200 $finish;
    end

endmodule

trafficv3.vcd
$date
	Sun Dec 14 08:27:47 2025
$end
$version
	Icarus Verilog
$end
$timescale
	1ps
$end
$scope module tb_smart_traffic_controller $end
$var wire 2 ! traffic_light [1:0] $end
$var wire 1 " pedestrian_green $end
$var wire 4 # parking_slots [3:0] $end
$var wire 1 $ emergency_active $end
$var reg 1 % car_enter $end
$var reg 1 & car_exit $end
$var reg 1 ' car_sensor $end
$var reg 1 ( clk $end
$var reg 1 ) emergency $end
$var reg 1 * pedestrian_req $end
$var reg 1 + reset $end
$scope module dut $end
$var wire 1 % car_enter $end
$var wire 1 & car_exit $end
$var wire 1 ' car_sensor $end
$var wire 1 ( clk $end
$var wire 1 ) emergency $end
$var wire 1 * pedestrian_req $end
$var wire 1 + reset $end
$var parameter 3 , s0_IDLE $end
$var parameter 3 - s1_GREEN $end
$var parameter 3 . s2_YELLOW $end
$var parameter 3 / s3_RED $end
$var parameter 3 0 s4_EMERGENCY $end
$var parameter 3 1 s5_PEDESTRIAN $end
$var reg 1 $ emergency_active $end
$var reg 3 2 next_state [2:0] $end
$var reg 4 3 parking_slots [3:0] $end
$var reg 1 " pedestrian_green $end
$var reg 3 4 state [2:0] $end
$var reg 4 5 timer [3:0] $end
$var reg 2 6 traffic_light [1:0] $end
$upscope $end
$upscope $end
$enddefinitions $end
$comment Show the parameter values. $end
$dumpall
b101 1
b100 0
b11 /
b10 .
b1 -
b0 ,
$end
#0
$dumpvars
b0 6
b0 5
b0 4
b1010 3
b0 2
1+
0*
0)
0(
0'
0&
0%
0$
b1010 #
0"
b0 !
$end
#5000
1(
#10000
0(
#15000
1(
#20000
0(
0+
#25000
b1 5
1(
#30000
0(
#35000
b10 5
1(
#40000
b1 2
0(
1'
#45000
b10 !
b10 6
b0 5
b1 4
1(
#50000
0(
0'
#55000
b1 5
1(
#60000
0(
#65000
b10 5
1(
#70000
0(
#75000
b11 5
1(
#80000
0(
#85000
b10 2
b100 5
1(
#90000
0(
#95000
b1 !
b1 6
b0 5
b10 4
1(
#100000
0(
#105000
b1 5
1(
#110000
0(
1*
#115000
b11 2
b10 5
1(
#120000
b11 2
0(
0*
#125000
b0 !
b0 6
b0 5
b11 4
1(
#130000
0(
#135000
b1 5
1(
#140000
0(
#145000
b10 5
1(
#150000
0(
#155000
b0 2
b11 5
1(
#160000
0(
#165000
b0 5
b0 4
1(
#170000
0(
#175000
b1 5
1(
#180000
0(
#185000
b10 5
1(
#190000
0(
#195000
b11 5
1(
#200000
b100 2
0(
1)
#205000
1$
b10 !
b10 6
b0 5
b100 4
1(
#210000
0(
#215000
b1 5
1(
#220000
0(
#225000
b10 5
1(
#230000
0(
#235000
b11 5
1(
#240000
b0 2
0(
0)
#245000
0$
b0 !
b0 6
b0 5
b0 4
1(
#250000
0(
#255000
b1 5
1(
#260000
0(
1%
#265000
b1001 #
b1001 3
b10 5
1(
#270000
0(
0%
#275000
b11 5
1(
#280000
0(
#285000
b100 5
1(
#290000
0(
1&
#295000
b1010 #
b1010 3
b101 5
1(
#300000
0(
0&
#305000
b110 5
1(
#310000
0(
#315000
b111 5
1(
#320000
0(
#325000
b1000 5
1(
#330000
0(
#335000
b1001 5
1(
#340000
0(
#345000
b1010 5
1(
#350000
0(
#355000
b1011 5
1(
#360000
0(
#365000
b1100 5
1(
#370000
0(
#375000
b1101 5
1(
#380000
0(
#385000
b1110 5
1(
#390000
0(
#395000
b1111 5
1(
#400000
0(
#405000
b0 5
1(
#410000
0(
#415000
b1 5
1(
#420000
0(
#425000
b10 5
1(
#430000
0(
#435000
b11 5
1(
#440000
0(
#445000
b100 5
1(
#450000
0(
#455000
b101 5
1(
#460000
0(
#465000
b110 5
1(
#470000
0(
#475000
b111 5
1(
#480000
0(
#485000
b1000 5
1(
#490000
0(
#495000
b1001 5
1(
